[
  {
    "division_name":"Texoma",
    "minLng":-97.1688557379,
    "minLat":33.4190043929,
    "maxLng":-96.3669197253,
    "maxLat":33.8997131742
  },
  {
    "division_name":"Justin",
    "minLng":-98.0214039277,
    "minLat":32.7333763927,
    "maxLng":-96.7577180462,
    "maxLat":33.634573664
  },
  {
    "division_name":"Cresson",
    "minLng":-98.1868067306,
    "minLat":31.9952662433,
    "maxLng":-97.3662087724,
    "maxLat":32.9777709846
  },
  {
    "division_name":"Mansfield",
    "minLng":-97.4320414637,
    "minLat":32.3789977586,
    "maxLng":-97.0042597633,
    "maxLat":32.7597625669
  },
  {
    "division_name":"Dallas",
    "minLng":-97.1242409332,
    "minLat":32.3193859018,
    "maxLng":-96.3098338639,
    "maxLat":33.0550037521
  },
  {
    "division_name":"Hillsboro",
    "minLng":-98.1458247903,
    "minLat":31.1459002753,
    "maxLng":-96.6837286726,
    "maxLat":32.4757073258
  },
  {
    "division_name":"Mexia",
    "minLng":-96.9243885775,
    "minLat":31.0162599991,
    "maxLng":-95.6213372665,
    "maxLat":32.0176518409
  },
  {
    "division_name":"Hearne",
    "minLng":-97.0687845204,
    "minLat":30.602868265,
    "maxLng":-95.8759484702,
    "maxLat":31.3558156692
  },
  {
    "division_name":"Bayou",
    "minLng":-95.0785301359,
    "minLat":29.1147401121,
    "maxLng":-93.9655976302,
    "maxLat":30.2685164418
  },
  {
    "division_name":"Dayton",
    "minLng":-95.4594150157,
    "minLat":29.6540573101,
    "maxLng":-94.5289820903,
    "maxLat":30.4575293628
  },
  {
    "division_name":"Houston",
    "minLng":-95.8138358462,
    "minLat":29.294063751,
    "maxLng":-94.9975787587,
    "maxLat":29.7785517
  },
  {
    "division_name":"Jersey Village",
    "minLng":-95.9545525588,
    "minLat":29.6898448658,
    "maxLng":-95.3615142423,
    "maxLat":30.2494601343
  },
  {
    "division_name":"Hearne",
    "minLng":-96.5860250663,
    "minLat":31.4980217001,
    "maxLng":-96.4703469146,
    "maxLat":31.5515931697
  },
  {
    "division_name":"San Marcos",
    "minLng":-98.4903954168,
    "minLat":29.3372365528,
    "maxLng":-97.2845383208,
    "maxLat":30.5021427551
  },
  {
    "division_name":"San Antonio",
    "minLng":-99.1323841199,
    "minLat":28.7782468142,
    "maxLng":-97.8213650678,
    "maxLat":30.0428458776
  },
  {
    "division_name":"Corpus",
    "minLng":-98.3486771617,
    "minLat":27.1858627004,
    "maxLng":-96.7762555332,
    "maxLat":28.9006337522
  },
  {
    "division_name":"McKinney",
    "minLng":-96.7586819134,
    "minLat":33.1188339953,
    "maxLng":-96.4933337544,
    "maxLat":33.2774329037
  }
]